excelrd/__init__.py
excelrd/__version__.py
excelrd/biffh.py
excelrd/book.py
excelrd/compdoc.py
excelrd/formatting.py
excelrd/formula.py
excelrd/sheet.py
excelrd/timemachine.py
excelrd/xldate.py
excelrd/xlsx.py
excelrd-3.0.0.data/scripts/runxlrd.py
excelrd-3.0.0.dist-info/LICENSE
excelrd-3.0.0.dist-info/METADATA
excelrd-3.0.0.dist-info/WHEEL
excelrd-3.0.0.dist-info/top_level.txt
excelrd-3.0.0.dist-info/RECORD
