Metadata-Version: 2.1
Name: excelrd
Version: 3.0.0
Summary: Library for developers to extract data from Microsoft Excel (tm) spreadsheet files
Home-page: https://github.com/thombashi/excelrd
Author: John Machin
Author-email: sjmachin@lexicon.net
Maintainer: Tsuyoshi Hombashi
Maintainer-email: tsuyoshi.hombashi@gmail.com
License: BSD
Keywords: xls,excel,spreadsheet,workbook
Classifier: Development Status :: 5 - Production/Stable
Classifier: Intended Audience :: Developers
Classifier: License :: OSI Approved :: BSD License
Classifier: Programming Language :: Python
Classifier: Programming Language :: Python :: 3
Classifier: Programming Language :: Python :: 3.7
Classifier: Programming Language :: Python :: 3.8
Classifier: Programming Language :: Python :: 3.9
Classifier: Programming Language :: Python :: 3.10
Classifier: Programming Language :: Python :: 3.11
Classifier: Programming Language :: Python :: 3 :: Only
Classifier: Programming Language :: Python :: Implementation :: CPython
Classifier: Programming Language :: Python :: Implementation :: PyPy
Classifier: Operating System :: OS Independent
Classifier: Topic :: Office/Business
Classifier: Topic :: Office/Business :: Financial :: Spreadsheet
Classifier: Topic :: Software Development :: Libraries :: Python Modules
Requires-Python: >=3.7
Provides-Extra: docs
Provides-Extra: dev
Provides-Extra: test
License-File: LICENSE
